pyevmasm/__init__.py
pyevmasm/__main__.py
pyevmasm/evmasm.py
ethtools_pyevmasm-0.2.4.dist-info/LICENSE
ethtools_pyevmasm-0.2.4.dist-info/METADATA
ethtools_pyevmasm-0.2.4.dist-info/WHEEL
ethtools_pyevmasm-0.2.4.dist-info/entry_points.txt
ethtools_pyevmasm-0.2.4.dist-info/top_level.txt
ethtools_pyevmasm-0.2.4.dist-info/RECORD
